krbticket/__init__.py
krbticket/command.py
krbticket/config.py
krbticket/ticket.py
krbticket/updater.py
krbticket-1.0.6.dist-info/LICENSE
krbticket-1.0.6.dist-info/METADATA
krbticket-1.0.6.dist-info/WHEEL
krbticket-1.0.6.dist-info/top_level.txt
krbticket-1.0.6.dist-info/RECORD
