Metadata-Version: 2.1
Name: krbticket
Version: 1.0.6
Summary: Kerberos Ticket Manager
Home-page: https://github.com/ksauzz/krbticket
Author: Kazuhiro Suzuki
Author-email: ksauzzmsg@gmail.com
License: UNKNOWN
Platform: UNKNOWN
Classifier: Programming Language :: Python :: 3
Classifier: License :: OSI Approved :: MIT License
Classifier: Operating System :: POSIX
Provides-Extra: test
